[
  {
    "census_blockid":"260339701003021",
    "current_wins":13.0,
    "avg_wins":12.0,
    "std_wins":0.0,
    "appearance_count":1,
    "first_seen":1755216000,
    "is_first_appearance":false,
    "z_score":null,
    "spike_ratio":1.0833333333,
    "flag_z_score":true,
    "flag_spike":false,
    "flag_first_appear":false,
    "flag_rare":true,
    "pct_of_total":0.8666666667,
    "flag_concentration":true,
    "should_suppress":true,
    "the_date":"2025-08-16",
    "state":"Michigan",
    "dma_name":"Traverse City-Cadillac, MI",
    "winner":"Spectrum",
    "loser":"Packerland Broadband"
  },
  {
    "census_blockid":"260339701003031",
    "current_wins":1.0,
    "avg_wins":0.0,
    "std_wins":0.0,
    "appearance_count":0,
    "first_seen":null,
    "is_first_appearance":true,
    "z_score":null,
    "spike_ratio":null,
    "flag_z_score":true,
    "flag_spike":true,
    "flag_first_appear":true,
    "flag_rare":false,
    "pct_of_total":0.0666666667,
    "flag_concentration":false,
    "should_suppress":true,
    "the_date":"2025-08-16",
    "state":"Michigan",
    "dma_name":"Traverse City-Cadillac, MI",
    "winner":"Spectrum",
    "loser":"Packerland Broadband"
  },
  {
    "census_blockid":"260339705001013",
    "current_wins":1.0,
    "avg_wins":0.0,
    "std_wins":0.0,
    "appearance_count":0,
    "first_seen":null,
    "is_first_appearance":true,
    "z_score":null,
    "spike_ratio":null,
    "flag_z_score":true,
    "flag_spike":true,
    "flag_first_appear":true,
    "flag_rare":false,
    "pct_of_total":0.0666666667,
    "flag_concentration":false,
    "should_suppress":true,
    "the_date":"2025-08-16",
    "state":"Michigan",
    "dma_name":"Traverse City-Cadillac, MI",
    "winner":"Spectrum",
    "loser":"Packerland Broadband"
  },
  {
    "census_blockid":"484391115451007",
    "current_wins":3.0,
    "avg_wins":1.0,
    "std_wins":0.0,
    "appearance_count":1,
    "first_seen":1755302400,
    "is_first_appearance":false,
    "z_score":null,
    "spike_ratio":3.0,
    "flag_z_score":true,
    "flag_spike":false,
    "flag_first_appear":false,
    "flag_rare":true,
    "pct_of_total":0.6,
    "flag_concentration":false,
    "should_suppress":true,
    "the_date":"2025-08-17",
    "state":"Texas",
    "dma_name":"Dallas-Ft. Worth, TX",
    "winner":"Apogee Telecom",
    "loser":"AT&T"
  },
  {
    "census_blockid":"481130192023019",
    "current_wins":1.0,
    "avg_wins":0.0,
    "std_wins":0.0,
    "appearance_count":0,
    "first_seen":null,
    "is_first_appearance":true,
    "z_score":null,
    "spike_ratio":null,
    "flag_z_score":true,
    "flag_spike":true,
    "flag_first_appear":true,
    "flag_rare":false,
    "pct_of_total":0.2,
    "flag_concentration":false,
    "should_suppress":true,
    "the_date":"2025-08-17",
    "state":"Texas",
    "dma_name":"Dallas-Ft. Worth, TX",
    "winner":"Apogee Telecom",
    "loser":"AT&T"
  },
  {
    "census_blockid":"484391219061003",
    "current_wins":1.0,
    "avg_wins":0.0,
    "std_wins":0.0,
    "appearance_count":0,
    "first_seen":null,
    "is_first_appearance":true,
    "z_score":null,
    "spike_ratio":null,
    "flag_z_score":true,
    "flag_spike":true,
    "flag_first_appear":true,
    "flag_rare":false,
    "pct_of_total":0.2,
    "flag_concentration":false,
    "should_suppress":true,
    "the_date":"2025-08-17",
    "state":"Texas",
    "dma_name":"Dallas-Ft. Worth, TX",
    "winner":"Apogee Telecom",
    "loser":"AT&T"
  },
  {
    "census_blockid":"060190014112007",
    "current_wins":1.0,
    "avg_wins":0.0,
    "std_wins":0.0,
    "appearance_count":1,
    "first_seen":1752710400,
    "is_first_appearance":false,
    "z_score":null,
    "spike_ratio":null,
    "flag_z_score":true,
    "flag_spike":true,
    "flag_first_appear":false,
    "flag_rare":true,
    "pct_of_total":0.05,
    "flag_concentration":false,
    "should_suppress":true,
    "the_date":"2025-08-15",
    "state":"California",
    "dma_name":"Fresno-Visalia, CA",
    "winner":"AT&T",
    "loser":"Comcast"
  },
  {
    "census_blockid":"060190026022012",
    "current_wins":3.0,
    "avg_wins":0.0,
    "std_wins":0.0,
    "appearance_count":1,
    "first_seen":1753920000,
    "is_first_appearance":false,
    "z_score":null,
    "spike_ratio":null,
    "flag_z_score":true,
    "flag_spike":true,
    "flag_first_appear":false,
    "flag_rare":true,
    "pct_of_total":0.15,
    "flag_concentration":false,
    "should_suppress":true,
    "the_date":"2025-08-15",
    "state":"California",
    "dma_name":"Fresno-Visalia, CA",
    "winner":"AT&T",
    "loser":"Comcast"
  },
  {
    "census_blockid":"060190037011004",
    "current_wins":1.0,
    "avg_wins":0.0,
    "std_wins":0.0,
    "appearance_count":1,
    "first_seen":1753315200,
    "is_first_appearance":false,
    "z_score":null,
    "spike_ratio":null,
    "flag_z_score":true,
    "flag_spike":true,
    "flag_first_appear":false,
    "flag_rare":true,
    "pct_of_total":0.05,
    "flag_concentration":false,
    "should_suppress":true,
    "the_date":"2025-08-15",
    "state":"California",
    "dma_name":"Fresno-Visalia, CA",
    "winner":"AT&T",
    "loser":"Comcast"
  },
  {
    "census_blockid":"060190038091005",
    "current_wins":2.0,
    "avg_wins":0.3333333333,
    "std_wins":0.5773502692,
    "appearance_count":3,
    "first_seen":1752710400,
    "is_first_appearance":false,
    "z_score":2.8867513459,
    "spike_ratio":6.0,
    "flag_z_score":false,
    "flag_spike":true,
    "flag_first_appear":false,
    "flag_rare":false,
    "pct_of_total":0.1,
    "flag_concentration":false,
    "should_suppress":true,
    "the_date":"2025-08-15",
    "state":"California",
    "dma_name":"Fresno-Visalia, CA",
    "winner":"AT&T",
    "loser":"Comcast"
  },
  {
    "census_blockid":"060190043022007",
    "current_wins":2.0,
    "avg_wins":1.0,
    "std_wins":0.0,
    "appearance_count":1,
    "first_seen":1755129600,
    "is_first_appearance":false,
    "z_score":null,
    "spike_ratio":2.0,
    "flag_z_score":true,
    "flag_spike":false,
    "flag_first_appear":false,
    "flag_rare":true,
    "pct_of_total":0.1,
    "flag_concentration":false,
    "should_suppress":true,
    "the_date":"2025-08-15",
    "state":"California",
    "dma_name":"Fresno-Visalia, CA",
    "winner":"AT&T",
    "loser":"Comcast"
  },
  {
    "census_blockid":"060190047033003",
    "current_wins":1.0,
    "avg_wins":0.5,
    "std_wins":0.7071067812,
    "appearance_count":2,
    "first_seen":1753315200,
    "is_first_appearance":false,
    "z_score":0.7071067812,
    "spike_ratio":2.0,
    "flag_z_score":false,
    "flag_spike":false,
    "flag_first_appear":false,
    "flag_rare":true,
    "pct_of_total":0.05,
    "flag_concentration":false,
    "should_suppress":false,
    "the_date":"2025-08-15",
    "state":"California",
    "dma_name":"Fresno-Visalia, CA",
    "winner":"AT&T",
    "loser":"Comcast"
  },
  {
    "census_blockid":"060190059071002",
    "current_wins":1.0,
    "avg_wins":1.5,
    "std_wins":0.7071067812,
    "appearance_count":2,
    "first_seen":1753920000,
    "is_first_appearance":false,
    "z_score":-0.7071067812,
    "spike_ratio":0.6666666667,
    "flag_z_score":false,
    "flag_spike":false,
    "flag_first_appear":false,
    "flag_rare":true,
    "pct_of_total":0.05,
    "flag_concentration":false,
    "should_suppress":false,
    "the_date":"2025-08-15",
    "state":"California",
    "dma_name":"Fresno-Visalia, CA",
    "winner":"AT&T",
    "loser":"Comcast"
  },
  {
    "census_blockid":"060190080003017",
    "current_wins":1.0,
    "avg_wins":0.5,
    "std_wins":0.7071067812,
    "appearance_count":2,
    "first_seen":1752710400,
    "is_first_appearance":false,
    "z_score":0.7071067812,
    "spike_ratio":2.0,
    "flag_z_score":false,
    "flag_spike":false,
    "flag_first_appear":false,
    "flag_rare":true,
    "pct_of_total":0.05,
    "flag_concentration":false,
    "should_suppress":false,
    "the_date":"2025-08-15",
    "state":"California",
    "dma_name":"Fresno-Visalia, CA",
    "winner":"AT&T",
    "loser":"Comcast"
  },
  {
    "census_blockid":"060190017003013",
    "current_wins":1.0,
    "avg_wins":0.0,
    "std_wins":0.0,
    "appearance_count":0,
    "first_seen":null,
    "is_first_appearance":true,
    "z_score":null,
    "spike_ratio":null,
    "flag_z_score":true,
    "flag_spike":true,
    "flag_first_appear":true,
    "flag_rare":false,
    "pct_of_total":0.05,
    "flag_concentration":false,
    "should_suppress":true,
    "the_date":"2025-08-15",
    "state":"California",
    "dma_name":"Fresno-Visalia, CA",
    "winner":"AT&T",
    "loser":"Comcast"
  },
  {
    "census_blockid":"060190026012000",
    "current_wins":1.0,
    "avg_wins":0.0,
    "std_wins":0.0,
    "appearance_count":0,
    "first_seen":null,
    "is_first_appearance":true,
    "z_score":null,
    "spike_ratio":null,
    "flag_z_score":true,
    "flag_spike":true,
    "flag_first_appear":true,
    "flag_rare":false,
    "pct_of_total":0.05,
    "flag_concentration":false,
    "should_suppress":true,
    "the_date":"2025-08-15",
    "state":"California",
    "dma_name":"Fresno-Visalia, CA",
    "winner":"AT&T",
    "loser":"Comcast"
  },
  {
    "census_blockid":"060190033024010",
    "current_wins":1.0,
    "avg_wins":0.0,
    "std_wins":0.0,
    "appearance_count":0,
    "first_seen":null,
    "is_first_appearance":true,
    "z_score":null,
    "spike_ratio":null,
    "flag_z_score":true,
    "flag_spike":true,
    "flag_first_appear":true,
    "flag_rare":false,
    "pct_of_total":0.05,
    "flag_concentration":false,
    "should_suppress":true,
    "the_date":"2025-08-15",
    "state":"California",
    "dma_name":"Fresno-Visalia, CA",
    "winner":"AT&T",
    "loser":"Comcast"
  },
  {
    "census_blockid":"060190036003000",
    "current_wins":1.0,
    "avg_wins":0.0,
    "std_wins":0.0,
    "appearance_count":0,
    "first_seen":null,
    "is_first_appearance":true,
    "z_score":null,
    "spike_ratio":null,
    "flag_z_score":true,
    "flag_spike":true,
    "flag_first_appear":true,
    "flag_rare":false,
    "pct_of_total":0.05,
    "flag_concentration":false,
    "should_suppress":true,
    "the_date":"2025-08-15",
    "state":"California",
    "dma_name":"Fresno-Visalia, CA",
    "winner":"AT&T",
    "loser":"Comcast"
  },
  {
    "census_blockid":"060190041001040",
    "current_wins":1.0,
    "avg_wins":0.0,
    "std_wins":0.0,
    "appearance_count":0,
    "first_seen":null,
    "is_first_appearance":true,
    "z_score":null,
    "spike_ratio":null,
    "flag_z_score":true,
    "flag_spike":true,
    "flag_first_appear":true,
    "flag_rare":false,
    "pct_of_total":0.05,
    "flag_concentration":false,
    "should_suppress":true,
    "the_date":"2025-08-15",
    "state":"California",
    "dma_name":"Fresno-Visalia, CA",
    "winner":"AT&T",
    "loser":"Comcast"
  },
  {
    "census_blockid":"060310016012013",
    "current_wins":1.0,
    "avg_wins":0.0,
    "std_wins":0.0,
    "appearance_count":0,
    "first_seen":null,
    "is_first_appearance":true,
    "z_score":null,
    "spike_ratio":null,
    "flag_z_score":true,
    "flag_spike":true,
    "flag_first_appear":true,
    "flag_rare":false,
    "pct_of_total":0.05,
    "flag_concentration":false,
    "should_suppress":true,
    "the_date":"2025-08-15",
    "state":"California",
    "dma_name":"Fresno-Visalia, CA",
    "winner":"AT&T",
    "loser":"Comcast"
  },
  {
    "census_blockid":"060390005093005",
    "current_wins":1.0,
    "avg_wins":0.0,
    "std_wins":0.0,
    "appearance_count":0,
    "first_seen":null,
    "is_first_appearance":true,
    "z_score":null,
    "spike_ratio":null,
    "flag_z_score":true,
    "flag_spike":true,
    "flag_first_appear":true,
    "flag_rare":false,
    "pct_of_total":0.05,
    "flag_concentration":false,
    "should_suppress":true,
    "the_date":"2025-08-15",
    "state":"California",
    "dma_name":"Fresno-Visalia, CA",
    "winner":"AT&T",
    "loser":"Comcast"
  },
  {
    "census_blockid":"060470016011003",
    "current_wins":1.0,
    "avg_wins":0.0,
    "std_wins":0.0,
    "appearance_count":0,
    "first_seen":null,
    "is_first_appearance":true,
    "z_score":null,
    "spike_ratio":null,
    "flag_z_score":true,
    "flag_spike":true,
    "flag_first_appear":true,
    "flag_rare":false,
    "pct_of_total":0.05,
    "flag_concentration":false,
    "should_suppress":true,
    "the_date":"2025-08-15",
    "state":"California",
    "dma_name":"Fresno-Visalia, CA",
    "winner":"AT&T",
    "loser":"Comcast"
  },
  {
    "census_blockid":"482013137002013",
    "current_wins":1.0,
    "avg_wins":0.0,
    "std_wins":0.0,
    "appearance_count":0,
    "first_seen":null,
    "is_first_appearance":true,
    "z_score":null,
    "spike_ratio":null,
    "flag_z_score":true,
    "flag_spike":true,
    "flag_first_appear":true,
    "flag_rare":false,
    "pct_of_total":1.0,
    "flag_concentration":true,
    "should_suppress":true,
    "the_date":"2025-08-17",
    "state":"Texas",
    "dma_name":"Houston, TX",
    "winner":"Pavlov Media",
    "loser":"AT&T"
  },
  {
    "census_blockid":"484391115451007",
    "current_wins":1.0,
    "avg_wins":1.0,
    "std_wins":0.0,
    "appearance_count":1,
    "first_seen":1754611200,
    "is_first_appearance":false,
    "z_score":null,
    "spike_ratio":1.0,
    "flag_z_score":true,
    "flag_spike":false,
    "flag_first_appear":false,
    "flag_rare":true,
    "pct_of_total":0.3333333333,
    "flag_concentration":false,
    "should_suppress":true,
    "the_date":"2025-08-16",
    "state":"Texas",
    "dma_name":"Dallas-Ft. Worth, TX",
    "winner":"Apogee Telecom",
    "loser":"AT&T"
  },
  {
    "census_blockid":"484391115063009",
    "current_wins":1.0,
    "avg_wins":0.0,
    "std_wins":0.0,
    "appearance_count":0,
    "first_seen":null,
    "is_first_appearance":true,
    "z_score":null,
    "spike_ratio":null,
    "flag_z_score":true,
    "flag_spike":true,
    "flag_first_appear":true,
    "flag_rare":false,
    "pct_of_total":0.3333333333,
    "flag_concentration":false,
    "should_suppress":true,
    "the_date":"2025-08-16",
    "state":"Texas",
    "dma_name":"Dallas-Ft. Worth, TX",
    "winner":"Apogee Telecom",
    "loser":"AT&T"
  },
  {
    "census_blockid":"484391222002021",
    "current_wins":1.0,
    "avg_wins":0.0,
    "std_wins":0.0,
    "appearance_count":0,
    "first_seen":null,
    "is_first_appearance":true,
    "z_score":null,
    "spike_ratio":null,
    "flag_z_score":true,
    "flag_spike":true,
    "flag_first_appear":true,
    "flag_rare":false,
    "pct_of_total":0.3333333333,
    "flag_concentration":false,
    "should_suppress":true,
    "the_date":"2025-08-16",
    "state":"Texas",
    "dma_name":"Dallas-Ft. Worth, TX",
    "winner":"Apogee Telecom",
    "loser":"AT&T"
  },
  {
    "census_blockid":"121050103001021",
    "current_wins":1.0,
    "avg_wins":0.0,
    "std_wins":0.0,
    "appearance_count":0,
    "first_seen":null,
    "is_first_appearance":true,
    "z_score":null,
    "spike_ratio":null,
    "flag_z_score":true,
    "flag_spike":true,
    "flag_first_appear":true,
    "flag_rare":false,
    "pct_of_total":0.25,
    "flag_concentration":false,
    "should_suppress":true,
    "the_date":"2025-08-15",
    "state":"Florida",
    "dma_name":"Tampa-St. Petersburg, FL",
    "winner":"Spectrum",
    "loser":"T-Mobile Fiber"
  },
  {
    "census_blockid":"121050110002004",
    "current_wins":1.0,
    "avg_wins":0.0,
    "std_wins":0.0,
    "appearance_count":0,
    "first_seen":null,
    "is_first_appearance":true,
    "z_score":null,
    "spike_ratio":null,
    "flag_z_score":true,
    "flag_spike":true,
    "flag_first_appear":true,
    "flag_rare":false,
    "pct_of_total":0.25,
    "flag_concentration":false,
    "should_suppress":true,
    "the_date":"2025-08-15",
    "state":"Florida",
    "dma_name":"Tampa-St. Petersburg, FL",
    "winner":"Spectrum",
    "loser":"T-Mobile Fiber"
  },
  {
    "census_blockid":"121050121251000",
    "current_wins":1.0,
    "avg_wins":0.0,
    "std_wins":0.0,
    "appearance_count":0,
    "first_seen":null,
    "is_first_appearance":true,
    "z_score":null,
    "spike_ratio":null,
    "flag_z_score":true,
    "flag_spike":true,
    "flag_first_appear":true,
    "flag_rare":false,
    "pct_of_total":0.25,
    "flag_concentration":false,
    "should_suppress":true,
    "the_date":"2025-08-15",
    "state":"Florida",
    "dma_name":"Tampa-St. Petersburg, FL",
    "winner":"Spectrum",
    "loser":"T-Mobile Fiber"
  },
  {
    "census_blockid":"121050121261001",
    "current_wins":1.0,
    "avg_wins":0.0,
    "std_wins":0.0,
    "appearance_count":0,
    "first_seen":null,
    "is_first_appearance":true,
    "z_score":null,
    "spike_ratio":null,
    "flag_z_score":true,
    "flag_spike":true,
    "flag_first_appear":true,
    "flag_rare":false,
    "pct_of_total":0.25,
    "flag_concentration":false,
    "should_suppress":true,
    "the_date":"2025-08-15",
    "state":"Florida",
    "dma_name":"Tampa-St. Petersburg, FL",
    "winner":"Spectrum",
    "loser":"T-Mobile Fiber"
  },
  {
    "census_blockid":"261270106002020",
    "current_wins":2.0,
    "avg_wins":1.0,
    "std_wins":0.0,
    "appearance_count":2,
    "first_seen":1752796800,
    "is_first_appearance":false,
    "z_score":null,
    "spike_ratio":2.0,
    "flag_z_score":true,
    "flag_spike":false,
    "flag_first_appear":false,
    "flag_rare":true,
    "pct_of_total":0.5,
    "flag_concentration":false,
    "should_suppress":true,
    "the_date":"2025-08-16",
    "state":"Michigan",
    "dma_name":"Grand Rapids-Kalamazoo-Battle Creek, MI",
    "winner":"Spectrum",
    "loser":"Hughes"
  },
  {
    "census_blockid":"260050312003022",
    "current_wins":1.0,
    "avg_wins":0.0,
    "std_wins":0.0,
    "appearance_count":0,
    "first_seen":null,
    "is_first_appearance":true,
    "z_score":null,
    "spike_ratio":null,
    "flag_z_score":true,
    "flag_spike":true,
    "flag_first_appear":true,
    "flag_rare":false,
    "pct_of_total":0.25,
    "flag_concentration":false,
    "should_suppress":true,
    "the_date":"2025-08-16",
    "state":"Michigan",
    "dma_name":"Grand Rapids-Kalamazoo-Battle Creek, MI",
    "winner":"Spectrum",
    "loser":"Hughes"
  },
  {
    "census_blockid":"261239707002025",
    "current_wins":1.0,
    "avg_wins":0.0,
    "std_wins":0.0,
    "appearance_count":0,
    "first_seen":null,
    "is_first_appearance":true,
    "z_score":null,
    "spike_ratio":null,
    "flag_z_score":true,
    "flag_spike":true,
    "flag_first_appear":true,
    "flag_rare":false,
    "pct_of_total":0.25,
    "flag_concentration":false,
    "should_suppress":true,
    "the_date":"2025-08-16",
    "state":"Michigan",
    "dma_name":"Grand Rapids-Kalamazoo-Battle Creek, MI",
    "winner":"Spectrum",
    "loser":"Hughes"
  },
  {
    "census_blockid":"390230013002009",
    "current_wins":1.0,
    "avg_wins":1.0,
    "std_wins":0.0,
    "appearance_count":1,
    "first_seen":1755216000,
    "is_first_appearance":false,
    "z_score":null,
    "spike_ratio":1.0,
    "flag_z_score":true,
    "flag_spike":false,
    "flag_first_appear":false,
    "flag_rare":true,
    "pct_of_total":0.0833333333,
    "flag_concentration":false,
    "should_suppress":true,
    "the_date":"2025-08-16",
    "state":"Ohio",
    "dma_name":"Dayton, OH",
    "winner":"AT&T",
    "loser":"Spectrum"
  },
  {
    "census_blockid":"390572103002024",
    "current_wins":1.0,
    "avg_wins":0.0,
    "std_wins":0.0,
    "appearance_count":1,
    "first_seen":1752796800,
    "is_first_appearance":false,
    "z_score":null,
    "spike_ratio":null,
    "flag_z_score":true,
    "flag_spike":true,
    "flag_first_appear":false,
    "flag_rare":true,
    "pct_of_total":0.0833333333,
    "flag_concentration":false,
    "should_suppress":true,
    "the_date":"2025-08-16",
    "state":"Ohio",
    "dma_name":"Dayton, OH",
    "winner":"AT&T",
    "loser":"Spectrum"
  },
  {
    "census_blockid":"391130002002003",
    "current_wins":1.0,
    "avg_wins":0.0,
    "std_wins":0.0,
    "appearance_count":1,
    "first_seen":1754006400,
    "is_first_appearance":false,
    "z_score":null,
    "spike_ratio":null,
    "flag_z_score":true,
    "flag_spike":true,
    "flag_first_appear":false,
    "flag_rare":true,
    "pct_of_total":0.0833333333,
    "flag_concentration":false,
    "should_suppress":true,
    "the_date":"2025-08-16",
    "state":"Ohio",
    "dma_name":"Dayton, OH",
    "winner":"AT&T",
    "loser":"Spectrum"
  },
  {
    "census_blockid":"391130404013012",
    "current_wins":1.0,
    "avg_wins":1.0,
    "std_wins":0.0,
    "appearance_count":1,
    "first_seen":1753401600,
    "is_first_appearance":false,
    "z_score":null,
    "spike_ratio":1.0,
    "flag_z_score":true,
    "flag_spike":false,
    "flag_first_appear":false,
    "flag_rare":true,
    "pct_of_total":0.0833333333,
    "flag_concentration":false,
    "should_suppress":true,
    "the_date":"2025-08-16",
    "state":"Ohio",
    "dma_name":"Dayton, OH",
    "winner":"AT&T",
    "loser":"Spectrum"
  },
  {
    "census_blockid":"391131004001017",
    "current_wins":1.0,
    "avg_wins":0.0,
    "std_wins":0.0,
    "appearance_count":1,
    "first_seen":1752796800,
    "is_first_appearance":false,
    "z_score":null,
    "spike_ratio":null,
    "flag_z_score":true,
    "flag_spike":true,
    "flag_first_appear":false,
    "flag_rare":true,
    "pct_of_total":0.0833333333,
    "flag_concentration":false,
    "should_suppress":true,
    "the_date":"2025-08-16",
    "state":"Ohio",
    "dma_name":"Dayton, OH",
    "winner":"AT&T",
    "loser":"Spectrum"
  },
  {
    "census_blockid":"391093651024041",
    "current_wins":1.0,
    "avg_wins":0.0,
    "std_wins":0.0,
    "appearance_count":0,
    "first_seen":null,
    "is_first_appearance":true,
    "z_score":null,
    "spike_ratio":null,
    "flag_z_score":true,
    "flag_spike":true,
    "flag_first_appear":true,
    "flag_rare":false,
    "pct_of_total":0.0833333333,
    "flag_concentration":false,
    "should_suppress":true,
    "the_date":"2025-08-16",
    "state":"Ohio",
    "dma_name":"Dayton, OH",
    "winner":"AT&T",
    "loser":"Spectrum"
  },
  {
    "census_blockid":"391130206022000",
    "current_wins":2.0,
    "avg_wins":0.0,
    "std_wins":0.0,
    "appearance_count":0,
    "first_seen":null,
    "is_first_appearance":true,
    "z_score":null,
    "spike_ratio":null,
    "flag_z_score":true,
    "flag_spike":true,
    "flag_first_appear":true,
    "flag_rare":false,
    "pct_of_total":0.1666666667,
    "flag_concentration":false,
    "should_suppress":true,
    "the_date":"2025-08-16",
    "state":"Ohio",
    "dma_name":"Dayton, OH",
    "winner":"AT&T",
    "loser":"Spectrum"
  },
  {
    "census_blockid":"391130214002000",
    "current_wins":1.0,
    "avg_wins":0.0,
    "std_wins":0.0,
    "appearance_count":0,
    "first_seen":null,
    "is_first_appearance":true,
    "z_score":null,
    "spike_ratio":null,
    "flag_z_score":true,
    "flag_spike":true,
    "flag_first_appear":true,
    "flag_rare":false,
    "pct_of_total":0.0833333333,
    "flag_concentration":false,
    "should_suppress":true,
    "the_date":"2025-08-16",
    "state":"Ohio",
    "dma_name":"Dayton, OH",
    "winner":"AT&T",
    "loser":"Spectrum"
  },
  {
    "census_blockid":"391130404013019",
    "current_wins":2.0,
    "avg_wins":0.0,
    "std_wins":0.0,
    "appearance_count":0,
    "first_seen":null,
    "is_first_appearance":true,
    "z_score":null,
    "spike_ratio":null,
    "flag_z_score":true,
    "flag_spike":true,
    "flag_first_appear":true,
    "flag_rare":false,
    "pct_of_total":0.1666666667,
    "flag_concentration":false,
    "should_suppress":true,
    "the_date":"2025-08-16",
    "state":"Ohio",
    "dma_name":"Dayton, OH",
    "winner":"AT&T",
    "loser":"Spectrum"
  },
  {
    "census_blockid":"391130805004008",
    "current_wins":1.0,
    "avg_wins":0.0,
    "std_wins":0.0,
    "appearance_count":0,
    "first_seen":null,
    "is_first_appearance":true,
    "z_score":null,
    "spike_ratio":null,
    "flag_z_score":true,
    "flag_spike":true,
    "flag_first_appear":true,
    "flag_rare":false,
    "pct_of_total":0.0833333333,
    "flag_concentration":false,
    "should_suppress":true,
    "the_date":"2025-08-16",
    "state":"Ohio",
    "dma_name":"Dayton, OH",
    "winner":"AT&T",
    "loser":"Spectrum"
  },
  {
    "census_blockid":"060730042001010",
    "current_wins":1.0,
    "avg_wins":0.0,
    "std_wins":0.0,
    "appearance_count":0,
    "first_seen":null,
    "is_first_appearance":true,
    "z_score":null,
    "spike_ratio":null,
    "flag_z_score":true,
    "flag_spike":true,
    "flag_first_appear":true,
    "flag_rare":false,
    "pct_of_total":0.5,
    "flag_concentration":false,
    "should_suppress":true,
    "the_date":"2025-08-15",
    "state":"California",
    "dma_name":"San Diego, CA",
    "winner":"Cox Communications",
    "loser":"Starlink"
  },
  {
    "census_blockid":"060730097061003",
    "current_wins":1.0,
    "avg_wins":0.0,
    "std_wins":0.0,
    "appearance_count":0,
    "first_seen":null,
    "is_first_appearance":true,
    "z_score":null,
    "spike_ratio":null,
    "flag_z_score":true,
    "flag_spike":true,
    "flag_first_appear":true,
    "flag_rare":false,
    "pct_of_total":0.5,
    "flag_concentration":false,
    "should_suppress":true,
    "the_date":"2025-08-15",
    "state":"California",
    "dma_name":"San Diego, CA",
    "winner":"Cox Communications",
    "loser":"Starlink"
  },
  {
    "census_blockid":"080410043003017",
    "current_wins":1.0,
    "avg_wins":0.0,
    "std_wins":0.0,
    "appearance_count":0,
    "first_seen":null,
    "is_first_appearance":true,
    "z_score":null,
    "spike_ratio":null,
    "flag_z_score":true,
    "flag_spike":true,
    "flag_first_appear":true,
    "flag_rare":false,
    "pct_of_total":1.0,
    "flag_concentration":true,
    "should_suppress":true,
    "the_date":"2025-06-19",
    "state":"Colorado",
    "dma_name":"Colorado Springs-Pueblo, CO",
    "winner":"CenturyLink",
    "loser":"AT&T"
  },
  {
    "census_blockid":"410390018011017",
    "current_wins":1.0,
    "avg_wins":1.0,
    "std_wins":0.0,
    "appearance_count":1,
    "first_seen":1755216000,
    "is_first_appearance":false,
    "z_score":null,
    "spike_ratio":1.0,
    "flag_z_score":true,
    "flag_spike":false,
    "flag_first_appear":false,
    "flag_rare":true,
    "pct_of_total":0.2,
    "flag_concentration":false,
    "should_suppress":true,
    "the_date":"2025-08-16",
    "state":"Oregon",
    "dma_name":"Eugene, OR",
    "winner":"CenturyLink",
    "loser":"Comcast"
  },
  {
    "census_blockid":"410390028001023",
    "current_wins":1.0,
    "avg_wins":0.0,
    "std_wins":0.0,
    "appearance_count":0,
    "first_seen":null,
    "is_first_appearance":true,
    "z_score":null,
    "spike_ratio":null,
    "flag_z_score":true,
    "flag_spike":true,
    "flag_first_appear":true,
    "flag_rare":false,
    "pct_of_total":0.2,
    "flag_concentration":false,
    "should_suppress":true,
    "the_date":"2025-08-16",
    "state":"Oregon",
    "dma_name":"Eugene, OR",
    "winner":"CenturyLink",
    "loser":"Comcast"
  },
  {
    "census_blockid":"410390050002016",
    "current_wins":1.0,
    "avg_wins":0.0,
    "std_wins":0.0,
    "appearance_count":0,
    "first_seen":null,
    "is_first_appearance":true,
    "z_score":null,
    "spike_ratio":null,
    "flag_z_score":true,
    "flag_spike":true,
    "flag_first_appear":true,
    "flag_rare":false,
    "pct_of_total":0.2,
    "flag_concentration":false,
    "should_suppress":true,
    "the_date":"2025-08-16",
    "state":"Oregon",
    "dma_name":"Eugene, OR",
    "winner":"CenturyLink",
    "loser":"Comcast"
  },
  {
    "census_blockid":"410390054003015",
    "current_wins":2.0,
    "avg_wins":0.0,
    "std_wins":0.0,
    "appearance_count":0,
    "first_seen":null,
    "is_first_appearance":true,
    "z_score":null,
    "spike_ratio":null,
    "flag_z_score":true,
    "flag_spike":true,
    "flag_first_appear":true,
    "flag_rare":false,
    "pct_of_total":0.4,
    "flag_concentration":false,
    "should_suppress":true,
    "the_date":"2025-08-16",
    "state":"Oregon",
    "dma_name":"Eugene, OR",
    "winner":"CenturyLink",
    "loser":"Comcast"
  },
  {
    "census_blockid":"482770010003021",
    "current_wins":1.0,
    "avg_wins":0.0,
    "std_wins":0.0,
    "appearance_count":0,
    "first_seen":null,
    "is_first_appearance":true,
    "z_score":null,
    "spike_ratio":null,
    "flag_z_score":true,
    "flag_spike":true,
    "flag_first_appear":true,
    "flag_rare":false,
    "pct_of_total":0.5,
    "flag_concentration":false,
    "should_suppress":true,
    "the_date":"2025-08-17",
    "state":"Texas",
    "dma_name":"Dallas-Ft. Worth, TX",
    "winner":"AT&T",
    "loser":"Starlink"
  },
  {
    "census_blockid":"484391142073004",
    "current_wins":1.0,
    "avg_wins":0.0,
    "std_wins":0.0,
    "appearance_count":0,
    "first_seen":null,
    "is_first_appearance":true,
    "z_score":null,
    "spike_ratio":null,
    "flag_z_score":true,
    "flag_spike":true,
    "flag_first_appear":true,
    "flag_rare":false,
    "pct_of_total":0.5,
    "flag_concentration":false,
    "should_suppress":true,
    "the_date":"2025-08-17",
    "state":"Texas",
    "dma_name":"Dallas-Ft. Worth, TX",
    "winner":"AT&T",
    "loser":"Starlink"
  },
  {
    "census_blockid":"011250117012014",
    "current_wins":1.0,
    "avg_wins":1.0,
    "std_wins":0.0,
    "appearance_count":2,
    "first_seen":1754697600,
    "is_first_appearance":false,
    "z_score":null,
    "spike_ratio":1.0,
    "flag_z_score":true,
    "flag_spike":false,
    "flag_first_appear":false,
    "flag_rare":true,
    "pct_of_total":0.3333333333,
    "flag_concentration":false,
    "should_suppress":true,
    "the_date":"2025-08-17",
    "state":"Alabama",
    "dma_name":"Birmingham, AL",
    "winner":"WhiteSky Communications",
    "loser":"Spectrum"
  },
  {
    "census_blockid":"011250123042011",
    "current_wins":1.0,
    "avg_wins":0.0,
    "std_wins":0.0,
    "appearance_count":0,
    "first_seen":null,
    "is_first_appearance":true,
    "z_score":null,
    "spike_ratio":null,
    "flag_z_score":true,
    "flag_spike":true,
    "flag_first_appear":true,
    "flag_rare":false,
    "pct_of_total":0.3333333333,
    "flag_concentration":false,
    "should_suppress":true,
    "the_date":"2025-08-17",
    "state":"Alabama",
    "dma_name":"Birmingham, AL",
    "winner":"WhiteSky Communications",
    "loser":"Spectrum"
  },
  {
    "census_blockid":"011250127002000",
    "current_wins":1.0,
    "avg_wins":0.0,
    "std_wins":0.0,
    "appearance_count":0,
    "first_seen":null,
    "is_first_appearance":true,
    "z_score":null,
    "spike_ratio":null,
    "flag_z_score":true,
    "flag_spike":true,
    "flag_first_appear":true,
    "flag_rare":false,
    "pct_of_total":0.3333333333,
    "flag_concentration":false,
    "should_suppress":true,
    "the_date":"2025-08-17",
    "state":"Alabama",
    "dma_name":"Birmingham, AL",
    "winner":"WhiteSky Communications",
    "loser":"Spectrum"
  },
  {
    "census_blockid":"060670055081000",
    "current_wins":1.0,
    "avg_wins":0.0,
    "std_wins":0.0,
    "appearance_count":1,
    "first_seen":1749600000,
    "is_first_appearance":false,
    "z_score":null,
    "spike_ratio":null,
    "flag_z_score":true,
    "flag_spike":true,
    "flag_first_appear":false,
    "flag_rare":true,
    "pct_of_total":0.3333333333,
    "flag_concentration":false,
    "should_suppress":true,
    "the_date":"2025-06-19",
    "state":"California",
    "dma_name":"Sacramento-Stockton-Modesto, CA",
    "winner":"Comcast",
    "loser":"Altice"
  },
  {
    "census_blockid":"060670080092003",
    "current_wins":1.0,
    "avg_wins":0.0,
    "std_wins":0.0,
    "appearance_count":0,
    "first_seen":null,
    "is_first_appearance":true,
    "z_score":null,
    "spike_ratio":null,
    "flag_z_score":true,
    "flag_spike":true,
    "flag_first_appear":true,
    "flag_rare":false,
    "pct_of_total":0.3333333333,
    "flag_concentration":false,
    "should_suppress":true,
    "the_date":"2025-06-19",
    "state":"California",
    "dma_name":"Sacramento-Stockton-Modesto, CA",
    "winner":"Comcast",
    "loser":"Altice"
  },
  {
    "census_blockid":"060670091111010",
    "current_wins":1.0,
    "avg_wins":0.0,
    "std_wins":0.0,
    "appearance_count":0,
    "first_seen":null,
    "is_first_appearance":true,
    "z_score":null,
    "spike_ratio":null,
    "flag_z_score":true,
    "flag_spike":true,
    "flag_first_appear":true,
    "flag_rare":false,
    "pct_of_total":0.3333333333,
    "flag_concentration":false,
    "should_suppress":true,
    "the_date":"2025-06-19",
    "state":"California",
    "dma_name":"Sacramento-Stockton-Modesto, CA",
    "winner":"Comcast",
    "loser":"Altice"
  },
  {
    "census_blockid":"400173009022011",
    "current_wins":1.0,
    "avg_wins":1.0,
    "std_wins":0.0,
    "appearance_count":1,
    "first_seen":1752796800,
    "is_first_appearance":false,
    "z_score":null,
    "spike_ratio":1.0,
    "flag_z_score":true,
    "flag_spike":false,
    "flag_first_appear":false,
    "flag_rare":true,
    "pct_of_total":0.0714285714,
    "flag_concentration":false,
    "should_suppress":true,
    "the_date":"2025-08-16",
    "state":"Oklahoma",
    "dma_name":"Oklahoma City, OK",
    "winner":"AT&T",
    "loser":"Cox Communications"
  },
  {
    "census_blockid":"400173009041022",
    "current_wins":1.0,
    "avg_wins":1.0,
    "std_wins":0.0,
    "appearance_count":1,
    "first_seen":1755216000,
    "is_first_appearance":false,
    "z_score":null,
    "spike_ratio":1.0,
    "flag_z_score":true,
    "flag_spike":false,
    "flag_first_appear":false,
    "flag_rare":true,
    "pct_of_total":0.0714285714,
    "flag_concentration":false,
    "should_suppress":true,
    "the_date":"2025-08-16",
    "state":"Oklahoma",
    "dma_name":"Oklahoma City, OK",
    "winner":"AT&T",
    "loser":"Cox Communications"
  },
  {
    "census_blockid":"400272008001014",
    "current_wins":1.0,
    "avg_wins":1.0,
    "std_wins":0.0,
    "appearance_count":2,
    "first_seen":1752796800,
    "is_first_appearance":false,
    "z_score":null,
    "spike_ratio":1.0,
    "flag_z_score":true,
    "flag_spike":false,
    "flag_first_appear":false,
    "flag_rare":true,
    "pct_of_total":0.0714285714,
    "flag_concentration":false,
    "should_suppress":true,
    "the_date":"2025-08-16",
    "state":"Oklahoma",
    "dma_name":"Oklahoma City, OK",
    "winner":"AT&T",
    "loser":"Cox Communications"
  },
  {
    "census_blockid":"401091066011004",
    "current_wins":1.0,
    "avg_wins":0.5,
    "std_wins":0.7071067812,
    "appearance_count":2,
    "first_seen":1754006400,
    "is_first_appearance":false,
    "z_score":0.7071067812,
    "spike_ratio":2.0,
    "flag_z_score":false,
    "flag_spike":false,
    "flag_first_appear":false,
    "flag_rare":true,
    "pct_of_total":0.0714285714,
    "flag_concentration":false,
    "should_suppress":false,
    "the_date":"2025-08-16",
    "state":"Oklahoma",
    "dma_name":"Oklahoma City, OK",
    "winner":"AT&T",
    "loser":"Cox Communications"
  },
  {
    "census_blockid":"400173014091018",
    "current_wins":1.0,
    "avg_wins":0.0,
    "std_wins":0.0,
    "appearance_count":0,
    "first_seen":null,
    "is_first_appearance":true,
    "z_score":null,
    "spike_ratio":null,
    "flag_z_score":true,
    "flag_spike":true,
    "flag_first_appear":true,
    "flag_rare":false,
    "pct_of_total":0.0714285714,
    "flag_concentration":false,
    "should_suppress":true,
    "the_date":"2025-08-16",
    "state":"Oklahoma",
    "dma_name":"Oklahoma City, OK",
    "winner":"AT&T",
    "loser":"Cox Communications"
  },
  {
    "census_blockid":"400272016091000",
    "current_wins":1.0,
    "avg_wins":0.0,
    "std_wins":0.0,
    "appearance_count":0,
    "first_seen":null,
    "is_first_appearance":true,
    "z_score":null,
    "spike_ratio":null,
    "flag_z_score":true,
    "flag_spike":true,
    "flag_first_appear":true,
    "flag_rare":false,
    "pct_of_total":0.0714285714,
    "flag_concentration":false,
    "should_suppress":true,
    "the_date":"2025-08-16",
    "state":"Oklahoma",
    "dma_name":"Oklahoma City, OK",
    "winner":"AT&T",
    "loser":"Cox Communications"
  },
  {
    "census_blockid":"400272023011025",
    "current_wins":1.0,
    "avg_wins":0.0,
    "std_wins":0.0,
    "appearance_count":0,
    "first_seen":null,
    "is_first_appearance":true,
    "z_score":null,
    "spike_ratio":null,
    "flag_z_score":true,
    "flag_spike":true,
    "flag_first_appear":true,
    "flag_rare":false,
    "pct_of_total":0.0714285714,
    "flag_concentration":false,
    "should_suppress":true,
    "the_date":"2025-08-16",
    "state":"Oklahoma",
    "dma_name":"Oklahoma City, OK",
    "winner":"AT&T",
    "loser":"Cox Communications"
  },
  {
    "census_blockid":"400496814004013",
    "current_wins":2.0,
    "avg_wins":0.0,
    "std_wins":0.0,
    "appearance_count":0,
    "first_seen":null,
    "is_first_appearance":true,
    "z_score":null,
    "spike_ratio":null,
    "flag_z_score":true,
    "flag_spike":true,
    "flag_first_appear":true,
    "flag_rare":false,
    "pct_of_total":0.1428571429,
    "flag_concentration":false,
    "should_suppress":true,
    "the_date":"2025-08-16",
    "state":"Oklahoma",
    "dma_name":"Oklahoma City, OK",
    "winner":"AT&T",
    "loser":"Cox Communications"
  },
  {
    "census_blockid":"401091039001001",
    "current_wins":2.0,
    "avg_wins":0.0,
    "std_wins":0.0,
    "appearance_count":0,
    "first_seen":null,
    "is_first_appearance":true,
    "z_score":null,
    "spike_ratio":null,
    "flag_z_score":true,
    "flag_spike":true,
    "flag_first_appear":true,
    "flag_rare":false,
    "pct_of_total":0.1428571429,
    "flag_concentration":false,
    "should_suppress":true,
    "the_date":"2025-08-16",
    "state":"Oklahoma",
    "dma_name":"Oklahoma City, OK",
    "winner":"AT&T",
    "loser":"Cox Communications"
  },
  {
    "census_blockid":"401091066083007",
    "current_wins":1.0,
    "avg_wins":0.0,
    "std_wins":0.0,
    "appearance_count":0,
    "first_seen":null,
    "is_first_appearance":true,
    "z_score":null,
    "spike_ratio":null,
    "flag_z_score":true,
    "flag_spike":true,
    "flag_first_appear":true,
    "flag_rare":false,
    "pct_of_total":0.0714285714,
    "flag_concentration":false,
    "should_suppress":true,
    "the_date":"2025-08-16",
    "state":"Oklahoma",
    "dma_name":"Oklahoma City, OK",
    "winner":"AT&T",
    "loser":"Cox Communications"
  },
  {
    "census_blockid":"401091077072000",
    "current_wins":1.0,
    "avg_wins":0.0,
    "std_wins":0.0,
    "appearance_count":0,
    "first_seen":null,
    "is_first_appearance":true,
    "z_score":null,
    "spike_ratio":null,
    "flag_z_score":true,
    "flag_spike":true,
    "flag_first_appear":true,
    "flag_rare":false,
    "pct_of_total":0.0714285714,
    "flag_concentration":false,
    "should_suppress":true,
    "the_date":"2025-08-16",
    "state":"Oklahoma",
    "dma_name":"Oklahoma City, OK",
    "winner":"AT&T",
    "loser":"Cox Communications"
  },
  {
    "census_blockid":"401091082172010",
    "current_wins":1.0,
    "avg_wins":0.0,
    "std_wins":0.0,
    "appearance_count":0,
    "first_seen":null,
    "is_first_appearance":true,
    "z_score":null,
    "spike_ratio":null,
    "flag_z_score":true,
    "flag_spike":true,
    "flag_first_appear":true,
    "flag_rare":false,
    "pct_of_total":0.0714285714,
    "flag_concentration":false,
    "should_suppress":true,
    "the_date":"2025-08-16",
    "state":"Oklahoma",
    "dma_name":"Oklahoma City, OK",
    "winner":"AT&T",
    "loser":"Cox Communications"
  },
  {
    "census_blockid":"240037022051001",
    "current_wins":2.0,
    "avg_wins":0.0,
    "std_wins":0.0,
    "appearance_count":0,
    "first_seen":null,
    "is_first_appearance":true,
    "z_score":null,
    "spike_ratio":null,
    "flag_z_score":true,
    "flag_spike":true,
    "flag_first_appear":true,
    "flag_rare":false,
    "pct_of_total":0.6666666667,
    "flag_concentration":false,
    "should_suppress":true,
    "the_date":"2025-08-15",
    "state":"Maryland",
    "dma_name":"Baltimore, MD",
    "winner":"T-Mobile FWA",
    "loser":"Brightspeed"
  },
  {
    "census_blockid":"245102502031013",
    "current_wins":1.0,
    "avg_wins":0.0,
    "std_wins":0.0,
    "appearance_count":0,
    "first_seen":null,
    "is_first_appearance":true,
    "z_score":null,
    "spike_ratio":null,
    "flag_z_score":true,
    "flag_spike":true,
    "flag_first_appear":true,
    "flag_rare":false,
    "pct_of_total":0.3333333333,
    "flag_concentration":false,
    "should_suppress":true,
    "the_date":"2025-08-15",
    "state":"Maryland",
    "dma_name":"Baltimore, MD",
    "winner":"T-Mobile FWA",
    "loser":"Brightspeed"
  },
  {
    "census_blockid":"482211602061004",
    "current_wins":1.0,
    "avg_wins":0.0,
    "std_wins":0.0,
    "appearance_count":0,
    "first_seen":null,
    "is_first_appearance":true,
    "z_score":null,
    "spike_ratio":null,
    "flag_z_score":true,
    "flag_spike":true,
    "flag_first_appear":true,
    "flag_rare":false,
    "pct_of_total":1.0,
    "flag_concentration":true,
    "should_suppress":true,
    "the_date":"2025-08-18",
    "state":"Texas",
    "dma_name":"Dallas-Ft. Worth, TX",
    "winner":"Spectrum",
    "loser":"Windstream"
  },
  {
    "census_blockid":"040159515014011",
    "current_wins":1.0,
    "avg_wins":0.0,
    "std_wins":0.0,
    "appearance_count":0,
    "first_seen":null,
    "is_first_appearance":true,
    "z_score":null,
    "spike_ratio":null,
    "flag_z_score":true,
    "flag_spike":true,
    "flag_first_appear":true,
    "flag_rare":false,
    "pct_of_total":1.0,
    "flag_concentration":true,
    "should_suppress":true,
    "the_date":"2025-06-19",
    "state":"Arizona",
    "dma_name":"Phoenix, AZ",
    "winner":"Altice",
    "loser":"Starlink"
  },
  {
    "census_blockid":"170190106011056",
    "current_wins":1.0,
    "avg_wins":0.0,
    "std_wins":0.0,
    "appearance_count":1,
    "first_seen":1754006400,
    "is_first_appearance":false,
    "z_score":null,
    "spike_ratio":null,
    "flag_z_score":true,
    "flag_spike":true,
    "flag_first_appear":false,
    "flag_rare":true,
    "pct_of_total":0.5,
    "flag_concentration":false,
    "should_suppress":true,
    "the_date":"2025-08-16",
    "state":"Illinois",
    "dma_name":"Champaign & Springfield-Decatur, IL",
    "winner":"Pavlov Media",
    "loser":"Comcast"
  },
  {
    "census_blockid":"170190005003016",
    "current_wins":1.0,
    "avg_wins":0.0,
    "std_wins":0.0,
    "appearance_count":0,
    "first_seen":null,
    "is_first_appearance":true,
    "z_score":null,
    "spike_ratio":null,
    "flag_z_score":true,
    "flag_spike":true,
    "flag_first_appear":true,
    "flag_rare":false,
    "pct_of_total":0.5,
    "flag_concentration":false,
    "should_suppress":true,
    "the_date":"2025-08-16",
    "state":"Illinois",
    "dma_name":"Champaign & Springfield-Decatur, IL",
    "winner":"Pavlov Media",
    "loser":"Comcast"
  },
  {
    "census_blockid":"060610237001006",
    "current_wins":1.0,
    "avg_wins":1.0,
    "std_wins":0.0,
    "appearance_count":1,
    "first_seen":1753488000,
    "is_first_appearance":false,
    "z_score":null,
    "spike_ratio":1.0,
    "flag_z_score":true,
    "flag_spike":false,
    "flag_first_appear":false,
    "flag_rare":true,
    "pct_of_total":0.037037037,
    "flag_concentration":false,
    "should_suppress":true,
    "the_date":"2025-08-17",
    "state":"California",
    "dma_name":"Sacramento-Stockton-Modesto, CA",
    "winner":"AT&T",
    "loser":"Comcast"
  },
  {
    "census_blockid":"060670032021006",
    "current_wins":1.0,
    "avg_wins":0.3333333333,
    "std_wins":0.5773502692,
    "appearance_count":3,
    "first_seen":1752883200,
    "is_first_appearance":false,
    "z_score":1.1547005384,
    "spike_ratio":3.0,
    "flag_z_score":false,
    "flag_spike":false,
    "flag_first_appear":false,
    "flag_rare":false,
    "pct_of_total":0.037037037,
    "flag_concentration":false,
    "should_suppress":false,
    "the_date":"2025-08-17",
    "state":"California",
    "dma_name":"Sacramento-Stockton-Modesto, CA",
    "winner":"AT&T",
    "loser":"Comcast"
  },
  {
    "census_blockid":"060670036001002",
    "current_wins":1.0,
    "avg_wins":0.0,
    "std_wins":0.0,
    "appearance_count":1,
    "first_seen":1754092800,
    "is_first_appearance":false,
    "z_score":null,
    "spike_ratio":null,
    "flag_z_score":true,
    "flag_spike":true,
    "flag_first_appear":false,
    "flag_rare":true,
    "pct_of_total":0.037037037,
    "flag_concentration":false,
    "should_suppress":true,
    "the_date":"2025-08-17",
    "state":"California",
    "dma_name":"Sacramento-Stockton-Modesto, CA",
    "winner":"AT&T",
    "loser":"Comcast"
  },
  {
    "census_blockid":"060670038001015",
    "current_wins":1.0,
    "avg_wins":0.5,
    "std_wins":0.7071067812,
    "appearance_count":2,
    "first_seen":1753488000,
    "is_first_appearance":false,
    "z_score":0.7071067812,
    "spike_ratio":2.0,
    "flag_z_score":false,
    "flag_spike":false,
    "flag_first_appear":false,
    "flag_rare":true,
    "pct_of_total":0.037037037,
    "flag_concentration":false,
    "should_suppress":false,
    "the_date":"2025-08-17",
    "state":"California",
    "dma_name":"Sacramento-Stockton-Modesto, CA",
    "winner":"AT&T",
    "loser":"Comcast"
  },
  {
    "census_blockid":"060670040082000",
    "current_wins":1.0,
    "avg_wins":0.6666666667,
    "std_wins":0.5773502692,
    "appearance_count":3,
    "first_seen":1752883200,
    "is_first_appearance":false,
    "z_score":0.5773502692,
    "spike_ratio":1.5,
    "flag_z_score":false,
    "flag_spike":false,
    "flag_first_appear":false,
    "flag_rare":false,
    "pct_of_total":0.037037037,
    "flag_concentration":false,
    "should_suppress":false,
    "the_date":"2025-08-17",
    "state":"California",
    "dma_name":"Sacramento-Stockton-Modesto, CA",
    "winner":"AT&T",
    "loser":"Comcast"
  },
  {
    "census_blockid":"060670041001010",
    "current_wins":1.0,
    "avg_wins":0.0,
    "std_wins":0.0,
    "appearance_count":2,
    "first_seen":1754092800,
    "is_first_appearance":false,
    "z_score":null,
    "spike_ratio":null,
    "flag_z_score":true,
    "flag_spike":true,
    "flag_first_appear":false,
    "flag_rare":true,
    "pct_of_total":0.037037037,
    "flag_concentration":false,
    "should_suppress":true,
    "the_date":"2025-08-17",
    "state":"California",
    "dma_name":"Sacramento-Stockton-Modesto, CA",
    "winner":"AT&T",
    "loser":"Comcast"
  },
  {
    "census_blockid":"060670054021000",
    "current_wins":1.0,
    "avg_wins":0.0,
    "std_wins":0.0,
    "appearance_count":2,
    "first_seen":1752883200,
    "is_first_appearance":false,
    "z_score":null,
    "spike_ratio":null,
    "flag_z_score":true,
    "flag_spike":true,
    "flag_first_appear":false,
    "flag_rare":true,
    "pct_of_total":0.037037037,
    "flag_concentration":false,
    "should_suppress":true,
    "the_date":"2025-08-17",
    "state":"California",
    "dma_name":"Sacramento-Stockton-Modesto, CA",
    "winner":"AT&T",
    "loser":"Comcast"
  },
  {
    "census_blockid":"060670057011006",
    "current_wins":1.0,
    "avg_wins":1.0,
    "std_wins":0.0,
    "appearance_count":2,
    "first_seen":1754697600,
    "is_first_appearance":false,
    "z_score":null,
    "spike_ratio":1.0,
    "flag_z_score":true,
    "flag_spike":false,
    "flag_first_appear":false,
    "flag_rare":true,
    "pct_of_total":0.037037037,
    "flag_concentration":false,
    "should_suppress":true,
    "the_date":"2025-08-17",
    "state":"California",
    "dma_name":"Sacramento-Stockton-Modesto, CA",
    "winner":"AT&T",
    "loser":"Comcast"
  },
  {
    "census_blockid":"060670066001010",
    "current_wins":1.0,
    "avg_wins":0.3333333333,
    "std_wins":0.5773502692,
    "appearance_count":3,
    "first_seen":1754092800,
    "is_first_appearance":false,
    "z_score":1.1547005384,
    "spike_ratio":3.0,
    "flag_z_score":false,
    "flag_spike":false,
    "flag_first_appear":false,
    "flag_rare":false,
    "pct_of_total":0.037037037,
    "flag_concentration":false,
    "should_suppress":false,
    "the_date":"2025-08-17",
    "state":"California",
    "dma_name":"Sacramento-Stockton-Modesto, CA",
    "winner":"AT&T",
    "loser":"Comcast"
  },
  {
    "census_blockid":"060670085082010",
    "current_wins":2.0,
    "avg_wins":1.0,
    "std_wins":0.0,
    "appearance_count":1,
    "first_seen":1754697600,
    "is_first_appearance":false,
    "z_score":null,
    "spike_ratio":2.0,
    "flag_z_score":true,
    "flag_spike":false,
    "flag_first_appear":false,
    "flag_rare":true,
    "pct_of_total":0.0740740741,
    "flag_concentration":false,
    "should_suppress":true,
    "the_date":"2025-08-17",
    "state":"California",
    "dma_name":"Sacramento-Stockton-Modesto, CA",
    "winner":"AT&T",
    "loser":"Comcast"
  },
  {
    "census_blockid":"060670087033002",
    "current_wins":3.0,
    "avg_wins":1.0,
    "std_wins":0.0,
    "appearance_count":2,
    "first_seen":1754092800,
    "is_first_appearance":false,
    "z_score":null,
    "spike_ratio":3.0,
    "flag_z_score":true,
    "flag_spike":false,
    "flag_first_appear":false,
    "flag_rare":true,
    "pct_of_total":0.1111111111,
    "flag_concentration":false,
    "should_suppress":true,
    "the_date":"2025-08-17",
    "state":"California",
    "dma_name":"Sacramento-Stockton-Modesto, CA",
    "winner":"AT&T",
    "loser":"Comcast"
  },
  {
    "census_blockid":"060670091111010",
    "current_wins":1.0,
    "avg_wins":1.0,
    "std_wins":0.0,
    "appearance_count":1,
    "first_seen":1753488000,
    "is_first_appearance":false,
    "z_score":null,
    "spike_ratio":1.0,
    "flag_z_score":true,
    "flag_spike":false,
    "flag_first_appear":false,
    "flag_rare":true,
    "pct_of_total":0.037037037,
    "flag_concentration":false,
    "should_suppress":true,
    "the_date":"2025-08-17",
    "state":"California",
    "dma_name":"Sacramento-Stockton-Modesto, CA",
    "winner":"AT&T",
    "loser":"Comcast"
  },
  {
    "census_blockid":"060770012003017",
    "current_wins":1.0,
    "avg_wins":0.4,
    "std_wins":0.5477225575,
    "appearance_count":5,
    "first_seen":1752883200,
    "is_first_appearance":false,
    "z_score":1.095445115,
    "spike_ratio":2.5,
    "flag_z_score":false,
    "flag_spike":false,
    "flag_first_appear":false,
    "flag_rare":false,
    "pct_of_total":0.037037037,
    "flag_concentration":false,
    "should_suppress":false,
    "the_date":"2025-08-17",
    "state":"California",
    "dma_name":"Sacramento-Stockton-Modesto, CA",
    "winner":"AT&T",
    "loser":"Comcast"
  },
  {
    "census_blockid":"060770033123000",
    "current_wins":2.0,
    "avg_wins":1.0,
    "std_wins":0.0,
    "appearance_count":1,
    "first_seen":1755302400,
    "is_first_appearance":false,
    "z_score":null,
    "spike_ratio":2.0,
    "flag_z_score":true,
    "flag_spike":false,
    "flag_first_appear":false,
    "flag_rare":true,
    "pct_of_total":0.0740740741,
    "flag_concentration":false,
    "should_suppress":true,
    "the_date":"2025-08-17",
    "state":"California",
    "dma_name":"Sacramento-Stockton-Modesto, CA",
    "winner":"AT&T",
    "loser":"Comcast"
  },
  {
    "census_blockid":"060990026023023",
    "current_wins":1.0,
    "avg_wins":1.0,
    "std_wins":0.0,
    "appearance_count":1,
    "first_seen":1754092800,
    "is_first_appearance":false,
    "z_score":null,
    "spike_ratio":1.0,
    "flag_z_score":true,
    "flag_spike":false,
    "flag_first_appear":false,
    "flag_rare":true,
    "pct_of_total":0.037037037,
    "flag_concentration":false,
    "should_suppress":true,
    "the_date":"2025-08-17",
    "state":"California",
    "dma_name":"Sacramento-Stockton-Modesto, CA",
    "winner":"AT&T",
    "loser":"Comcast"
  },
  {
    "census_blockid":"061010505012006",
    "current_wins":1.0,
    "avg_wins":0.0,
    "std_wins":0.0,
    "appearance_count":1,
    "first_seen":1754092800,
    "is_first_appearance":false,
    "z_score":null,
    "spike_ratio":null,
    "flag_z_score":true,
    "flag_spike":true,
    "flag_first_appear":false,
    "flag_rare":true,
    "pct_of_total":0.037037037,
    "flag_concentration":false,
    "should_suppress":true,
    "the_date":"2025-08-17",
    "state":"California",
    "dma_name":"Sacramento-Stockton-Modesto, CA",
    "winner":"AT&T",
    "loser":"Comcast"
  },
  {
    "census_blockid":"060610209083016",
    "current_wins":1.0,
    "avg_wins":0.0,
    "std_wins":0.0,
    "appearance_count":0,
    "first_seen":null,
    "is_first_appearance":true,
    "z_score":null,
    "spike_ratio":null,
    "flag_z_score":true,
    "flag_spike":true,
    "flag_first_appear":true,
    "flag_rare":false,
    "pct_of_total":0.037037037,
    "flag_concentration":false,
    "should_suppress":true,
    "the_date":"2025-08-17",
    "state":"California",
    "dma_name":"Sacramento-Stockton-Modesto, CA",
    "winner":"AT&T",
    "loser":"Comcast"
  },
  {
    "census_blockid":"060610216042029",
    "current_wins":1.0,
    "avg_wins":0.0,
    "std_wins":0.0,
    "appearance_count":0,
    "first_seen":null,
    "is_first_appearance":true,
    "z_score":null,
    "spike_ratio":null,
    "flag_z_score":true,
    "flag_spike":true,
    "flag_first_appear":true,
    "flag_rare":false,
    "pct_of_total":0.037037037,
    "flag_concentration":false,
    "should_suppress":true,
    "the_date":"2025-08-17",
    "state":"California",
    "dma_name":"Sacramento-Stockton-Modesto, CA",
    "winner":"AT&T",
    "loser":"Comcast"
  },
  {
    "census_blockid":"060670093191005",
    "current_wins":1.0,
    "avg_wins":0.0,
    "std_wins":0.0,
    "appearance_count":0,
    "first_seen":null,
    "is_first_appearance":true,
    "z_score":null,
    "spike_ratio":null,
    "flag_z_score":true,
    "flag_spike":true,
    "flag_first_appear":true,
    "flag_rare":false,
    "pct_of_total":0.037037037,
    "flag_concentration":false,
    "should_suppress":true,
    "the_date":"2025-08-17",
    "state":"California",
    "dma_name":"Sacramento-Stockton-Modesto, CA",
    "winner":"AT&T",
    "loser":"Comcast"
  },
  {
    "census_blockid":"060770032031004",
    "current_wins":1.0,
    "avg_wins":0.0,
    "std_wins":0.0,
    "appearance_count":0,
    "first_seen":null,
    "is_first_appearance":true,
    "z_score":null,
    "spike_ratio":null,
    "flag_z_score":true,
    "flag_spike":true,
    "flag_first_appear":true,
    "flag_rare":false,
    "pct_of_total":0.037037037,
    "flag_concentration":false,
    "should_suppress":true,
    "the_date":"2025-08-17",
    "state":"California",
    "dma_name":"Sacramento-Stockton-Modesto, CA",
    "winner":"AT&T",
    "loser":"Comcast"
  },
  {
    "census_blockid":"060952526102008",
    "current_wins":1.0,
    "avg_wins":0.0,
    "std_wins":0.0,
    "appearance_count":0,
    "first_seen":null,
    "is_first_appearance":true,
    "z_score":null,
    "spike_ratio":null,
    "flag_z_score":true,
    "flag_spike":true,
    "flag_first_appear":true,
    "flag_rare":false,
    "pct_of_total":0.037037037,
    "flag_concentration":false,
    "should_suppress":true,
    "the_date":"2025-08-17",
    "state":"California",
    "dma_name":"Sacramento-Stockton-Modesto, CA",
    "winner":"AT&T",
    "loser":"Comcast"
  },
  {
    "census_blockid":"060952529033009",
    "current_wins":1.0,
    "avg_wins":0.0,
    "std_wins":0.0,
    "appearance_count":0,
    "first_seen":null,
    "is_first_appearance":true,
    "z_score":null,
    "spike_ratio":null,
    "flag_z_score":true,
    "flag_spike":true,
    "flag_first_appear":true,
    "flag_rare":false,
    "pct_of_total":0.037037037,
    "flag_concentration":false,
    "should_suppress":true,
    "the_date":"2025-08-17",
    "state":"California",
    "dma_name":"Sacramento-Stockton-Modesto, CA",
    "winner":"AT&T",
    "loser":"Comcast"
  },
  {
    "census_blockid":"060990008033014",
    "current_wins":1.0,
    "avg_wins":0.0,
    "std_wins":0.0,
    "appearance_count":0,
    "first_seen":null,
    "is_first_appearance":true,
    "z_score":null,
    "spike_ratio":null,
    "flag_z_score":true,
    "flag_spike":true,
    "flag_first_appear":true,
    "flag_rare":false,
    "pct_of_total":0.037037037,
    "flag_concentration":false,
    "should_suppress":true,
    "the_date":"2025-08-17",
    "state":"California",
    "dma_name":"Sacramento-Stockton-Modesto, CA",
    "winner":"AT&T",
    "loser":"Comcast"
  },
  {
    "census_blockid":"060730171072003",
    "current_wins":1.0,
    "avg_wins":2.0,
    "std_wins":0.0,
    "appearance_count":1,
    "first_seen":1750204800,
    "is_first_appearance":false,
    "z_score":null,
    "spike_ratio":0.5,
    "flag_z_score":true,
    "flag_spike":false,
    "flag_first_appear":false,
    "flag_rare":true,
    "pct_of_total":0.25,
    "flag_concentration":false,
    "should_suppress":true,
    "the_date":"2025-06-19",
    "state":"California",
    "dma_name":"San Diego, CA",
    "winner":"AT&T",
    "loser":"Wyyerd Communications"
  },
  {
    "census_blockid":"060730133033006",
    "current_wins":1.0,
    "avg_wins":0.0,
    "std_wins":0.0,
    "appearance_count":0,
    "first_seen":null,
    "is_first_appearance":true,
    "z_score":null,
    "spike_ratio":null,
    "flag_z_score":true,
    "flag_spike":true,
    "flag_first_appear":true,
    "flag_rare":false,
    "pct_of_total":0.25,
    "flag_concentration":false,
    "should_suppress":true,
    "the_date":"2025-06-19",
    "state":"California",
    "dma_name":"San Diego, CA",
    "winner":"AT&T",
    "loser":"Wyyerd Communications"
  },
  {
    "census_blockid":"060730134144000",
    "current_wins":1.0,
    "avg_wins":0.0,
    "std_wins":0.0,
    "appearance_count":0,
    "first_seen":null,
    "is_first_appearance":true,
    "z_score":null,
    "spike_ratio":null,
    "flag_z_score":true,
    "flag_spike":true,
    "flag_first_appear":true,
    "flag_rare":false,
    "pct_of_total":0.25,
    "flag_concentration":false,
    "should_suppress":true,
    "the_date":"2025-06-19",
    "state":"California",
    "dma_name":"San Diego, CA",
    "winner":"AT&T",
    "loser":"Wyyerd Communications"
  },
  {
    "census_blockid":"060730177021006",
    "current_wins":1.0,
    "avg_wins":0.0,
    "std_wins":0.0,
    "appearance_count":0,
    "first_seen":null,
    "is_first_appearance":true,
    "z_score":null,
    "spike_ratio":null,
    "flag_z_score":true,
    "flag_spike":true,
    "flag_first_appear":true,
    "flag_rare":false,
    "pct_of_total":0.25,
    "flag_concentration":false,
    "should_suppress":true,
    "the_date":"2025-06-19",
    "state":"California",
    "dma_name":"San Diego, CA",
    "winner":"AT&T",
    "loser":"Wyyerd Communications"
  },
  {
    "census_blockid":"550419504001045",
    "current_wins":1.0,
    "avg_wins":0.0,
    "std_wins":0.0,
    "appearance_count":0,
    "first_seen":null,
    "is_first_appearance":true,
    "z_score":null,
    "spike_ratio":null,
    "flag_z_score":true,
    "flag_spike":true,
    "flag_first_appear":true,
    "flag_rare":false,
    "pct_of_total":1.0,
    "flag_concentration":true,
    "should_suppress":true,
    "the_date":"2025-06-19",
    "state":"Wisconsin",
    "dma_name":"Wausau-Rhinelander, WI",
    "winner":"Spectrum",
    "loser":"AT&T"
  }
]